README.md
setup.py
pylinux/__init__.py
pylinux2.egg-info/PKG-INFO
pylinux2.egg-info/SOURCES.txt
pylinux2.egg-info/dependency_links.txt
pylinux2.egg-info/not-zip-safe
pylinux2.egg-info/requires.txt
pylinux2.egg-info/top_level.txt
pylinux/common/__init__.py
pylinux/common/default_settings.py
pylinux/common/acessor/__init__.py
pylinux/common/acessor/base_accessor.py
pylinux/common/acessor/line_setting_accessor.py
pylinux/common/acessor/rc_local_accessor.py
pylinux/common/enum/__init__.py
pylinux/common/enum/blk_type_enum.py
pylinux/common/file_config/__init__.py
pylinux/common/file_config/file_config.py
pylinux/common/file_config/line_setting_file_config.py
pylinux/common/file_config/rc_local_file_config.py
pylinux/common/util/__init__.py
pylinux/common/util/command_util.py
pylinux/common/util/file_util.py
pylinux/config_file/__init__.py
pylinux/config_file/base_config_file.py
pylinux/exception/__init__.py
pylinux/exception/name_not_valid_exception.py
pylinux/exception/setting_not_found_exception.py
pylinux/exception/setting_not_valid_exception.py
pylinux/io/__init__.py
pylinux/io/block.py
pylinux/system_file/__init__.py
pylinux/system_file/base_system_file.py
pylinux/system_file/line_setting_file.py
pylinux/system_file/rc_local.py
tests/__init__.py
tests/context.py
tests/test_base_system_file.py
tests/test_main.py
tests/test_rc_local.py
tests/common/__init__.py
tests/common/base_test.py
tests/io/__init__.py
tests/io/test_block.py