Metadata-Version: 1.0
Name: pylinux2
Version: 0.10
Summary: a python library which helps to access linux resources
Home-page: https://github.com/ruiruige
Author: ruiruige
Author-email: whx20202@gmail.com
License: UNKNOWN
Keywords: python linux resource
Platform: UNKNOWN
